base116676/base.py
base116676/codes.py
base116676/gencodes.py
base116676/minimize.py
base116676/twitput.py
base116676-0.0.post1.dist-info/DESCRIPTION.rst
base116676-0.0.post1.dist-info/METADATA
base116676-0.0.post1.dist-info/RECORD
base116676-0.0.post1.dist-info/WHEEL
base116676-0.0.post1.dist-info/metadata.json
base116676-0.0.post1.dist-info/top_level.txt
