Metadata-Version: 2.0
Name: base116676
Version: 0.0.post1
Summary: Cram data in a small number of code points
Home-page: https://github.com/gvx/base116676
Author: Robin Wellner
Author-email: gyvox.public@gmail.com
License: ISC
Keywords: unicode compression twitter
Platform: UNKNOWN
Classifier: Development Status :: 3 - Alpha
Classifier: Intended Audience :: Developers
Classifier: Topic :: Software Development :: Build Tools
Classifier: License :: OSI Approved :: ISC License (ISCL)
Classifier: Programming Language :: Python :: 3
Classifier: Programming Language :: Python :: 3.3
Classifier: Programming Language :: Python :: 3.4
Classifier: Programming Language :: Python :: 3.5
Classifier: Topic :: Database
Requires-Dist: docopt
Requires-Dist: tweepy
